tg_scrape_comments/__init__.py
tg_scrape_comments/cli.py
tg_scrape_comments-0.1.3.dist-info/licenses/LICENSE
tg_scrape_comments-0.1.3.dist-info/METADATA
tg_scrape_comments-0.1.3.dist-info/WHEEL
tg_scrape_comments-0.1.3.dist-info/entry_points.txt
tg_scrape_comments-0.1.3.dist-info/top_level.txt
tg_scrape_comments-0.1.3.dist-info/RECORD
