Metadata-Version: 2.4
Name: tg-scrape-comments
Version: 0.1.3
Summary: Telegram channel posts & comments scraper (JSONL per channel)
Author: Anna Chizhik
License: MIT License
Project-URL: Homepage, https://github.com/Frantsuzova/tg_scrape_comments
Project-URL: Source, https://github.com/Frantsuzova/tg_scrape_comments
Project-URL: Issues, https://github.com/Frantsuzova/tg_scrape_comments/issues
Keywords: telegram,telethon,scraper,comments,jsonl
Classifier: Programming Language :: Python :: 3
Classifier: Programming Language :: Python :: 3 :: Only
Classifier: Programming Language :: Python :: 3.10
Classifier: Programming Language :: Python :: 3.11
Classifier: Programming Language :: Python :: 3.12
Classifier: License :: OSI Approved :: MIT License
Classifier: Environment :: Console
Classifier: Operating System :: OS Independent
Requires-Python: >=3.10
License-File: LICENSE
Requires-Dist: telethon>=1.36.0
Requires-Dist: tqdm>=4.66.0
Dynamic: license-file
